wechat_sdk_gmdzy2010/__init__.py
wechat_sdk_gmdzy2010/authority_request.py
wechat_sdk_gmdzy2010/base_request.py
wechat_sdk_gmdzy2010/exceptions.py
wechat_sdk_gmdzy2010/settings.py
wechat_sdk_gmdzy2010/utilites.py
wechat_sdk_gmdzy2010-0.3.3.dist-info/DESCRIPTION.rst
wechat_sdk_gmdzy2010-0.3.3.dist-info/METADATA
wechat_sdk_gmdzy2010-0.3.3.dist-info/RECORD
wechat_sdk_gmdzy2010-0.3.3.dist-info/WHEEL
wechat_sdk_gmdzy2010-0.3.3.dist-info/metadata.json
wechat_sdk_gmdzy2010-0.3.3.dist-info/top_level.txt
