Metadata-Version: 2.0
Name: wechat-sdk-gmdzy2010
Version: 0.3.3
Summary: The non-official sdk of wechat
Home-page: https://github.com/gmdzy2010/wechat_sdk_gmdzy2010
Author: gmdzy2010
Author-email: gmdzy2010@126.com
License: MIT License
Keywords: wechat
Platform: UNKNOWN
Classifier: Programming Language :: Python :: 3
Classifier: Programming Language :: Python :: 3.4
Classifier: Programming Language :: Python :: 3.5
Classifier: Programming Language :: Python :: 3.6
Classifier: License :: OSI Approved :: MIT License
Classifier: Operating System :: OS Independent
